Metadata-Version: 2.1
Name: Flask-Admin-reboot
Version: 1.6.1
Summary: Simple and extensible admin interface framework for Flask
Home-page: https://github.com/flask-admin/flask-admin/
Author: Flask-Admin team
Author-email: serge.koval+github@gmail.com
License: BSD
Platform: any
Classifier: Development Status :: 4 - Beta
Classifier: Environment :: Web Environment
Classifier: Intended Audience :: Developers
Classifier: License :: OSI Approved :: BSD License
Classifier: Operating System :: OS Independent
Classifier: Programming Language :: Python
Classifier: Topic :: Software Development :: Libraries :: Python Modules
Classifier: Programming Language :: Python :: 3.6
Classifier: Programming Language :: Python :: 3.7
Classifier: Programming Language :: Python :: 3.8
Classifier: Programming Language :: Python :: 3.9
Classifier: Programming Language :: Python :: 3.10
Classifier: Programming Language :: Python :: 3.11
Requires-Python: >=3.6
Provides-Extra: aws
Provides-Extra: azure
License-File: LICENSE
License-File: NOTICE
License-File: AUTHORS
